README.rst
setup.py
dealtape/__init__.py
dealtape/api.py
dealtape/auth.py
dealtape/models.py
dealtape_python_sdk.egg-info/PKG-INFO
dealtape_python_sdk.egg-info/SOURCES.txt
dealtape_python_sdk.egg-info/dependency_links.txt
dealtape_python_sdk.egg-info/requires.txt
dealtape_python_sdk.egg-info/top_level.txt