Metadata-Version: 1.0
Name: dealtape-python-sdk
Version: 0.0.1
Summary: DealTape SDK for Python
Home-page: https://github.com/rcrai/dealtape-python-sdk
Author: Yutao Zhang
Author-email: yutao@recurrent.ai
License: MIT
Platform: any
